xonia/__init__.py
xonia/asset.py
xonia/client.py
xonia/config.py
xonia/credentials.py
xonia/errors.py
xonia/message.py
xonia/token.py
xonia/user.py
xonia/utils.py
xonia.py-0.1.0.dist-info/LICENSE
xonia.py-0.1.0.dist-info/METADATA
xonia.py-0.1.0.dist-info/WHEEL
xonia.py-0.1.0.dist-info/top_level.txt
xonia.py-0.1.0.dist-info/RECORD
