Metadata-Version: 2.1
Name: xonia.py
Version: 0.1.0
Summary: xonia.py - An easy to use, and async API wrapper for Xonia written in Python.
Author-email: sqdnoises <sqdnoises.ash@gmail.com>
License: The MIT License (MIT)        
Project-URL: Homepage, https://github.com/sqdnoises/xonia.py
Keywords: xonia,api,wrapper,async
Classifier: Programming Language :: Python :: 3
Classifier: License :: OSI Approved :: MIT License
Classifier: Operating System :: OS Independent
Requires-Python: >=3.8
License-File: LICENSE
Requires-Dist: aiohttp
Requires-Dist: aiodns
Requires-Dist: yarl
Requires-Dist: requests
